{"data": [{"country": "Federal Republic of Nigeria", "confirmed": 49, "disease": "Lassa fever", "date": "14, February, 2019"}, {"country": "Democratic Republic of the Congo", "confirmed": 146, "disease": "Ebola hemorrhagic fever", "date": "01, February, 2019"}, {"country": "Democratic Republic of the Congo", "confirmed": 146, "disease": "Ebola hemorrhagic fever", "date": "01, February, 2019"}, {"country": "Democratic Republic of the Congo", "confirmed": 146, "disease": "Ebola hemorrhagic fever", "date": "01, February, 2019"}, {"country": "Federative Republic of Brazil", "confirmed": 2, "disease": "yellow fever", "date": "01, January, 2005"}, {"country": "Jamaica", "confirmed": 3, "disease": "dengue disease", "date": "01, January, 1990"}]}